UnleashSDK/__init__.py
UnleashSDK/unleashSDK.py
UnleashSDK-1.0.0.dist-info/METADATA
UnleashSDK-1.0.0.dist-info/WHEEL
UnleashSDK-1.0.0.dist-info/top_level.txt
UnleashSDK-1.0.0.dist-info/RECORD
