Metadata-Version: 2.1
Name: UnleashSDK
Version: 1.0.0
Summary: A python wrapper for the Unleash Nfts API
Home-page: https://github.com/kbm9696/Unleash-SDK
Author: Balamurugan
Author-email: balamurugankarikalan.96@gmail.com
License: GNU General Public License v3.0
Platform: UNKNOWN
Requires-Dist: requests
